{
    "x": 0,
    "y": 0,
    "things": [
        {
            "id": "0",
            "kind": "node",
            "text": "",
            "text_lines": [
                "INDUSTRY {name: \"wine\"}"
            ],
            "x": 632,
            "y": 400,
            "w": 0,
            "h": 0,
            "w_min": 32,
            "h_min": 8,
            "focus": false,
            "node_start": null,
            "node_end": null,
            "edge_direction": 0,
            "entity_type": ""
        },
        {
            "id": "1",
            "kind": "node",
            "text": "",
            "text_lines": [
                "SUBSTANCE {name: \"ozone\"}"
            ],
            "x": 632,
            "y": 176,
            "w": 0,
            "h": 0,
            "w_min": 32,
            "h_min": 8,
            "focus": false,
            "node_start": null,
            "node_end": null,
            "edge_direction": 0,
            "entity_type": ""
        },
        {
            "id": "2",
            "kind": "edge",
            "text": "",
            "text_lines": [],
            "x": 0,
            "y": 0,
            "w": 0,
            "h": 0,
            "w_min": 0,
            "h_min": 0,
            "focus": false,
            "node_start": {
                "id": "1",
                "kind": "node",
                "text": "",
                "text_lines": [
                    "SUBSTANCE {name: \"ozone\"}"
                ],
                "x": 632,
                "y": 176,
                "w": 0,
                "h": 0,
                "w_min": 32,
                "h_min": 8,
                "focus": false,
                "node_start": null,
                "node_end": null,
                "edge_direction": 0,
                "entity_type": ""
            },
            "node_end": {
                "id": "0",
                "kind": "node",
                "text": "",
                "text_lines": [
                    "INDUSTRY {name: \"wine\"}"
                ],
                "x": 632,
                "y": 400,
                "w": 0,
                "h": 0,
                "w_min": 32,
                "h_min": 8,
                "focus": false,
                "node_start": null,
                "node_end": null,
                "edge_direction": 0,
                "entity_type": ""
            },
            "edge_direction": 0,
            "entity_type": ""
        }
    ]
}